PLCSQL/PLCSQL.py
PLCSQL/__init__.py
PLCSQL-0.7.dist-info/METADATA
PLCSQL-0.7.dist-info/WHEEL
PLCSQL-0.7.dist-info/license.txt
PLCSQL-0.7.dist-info/top_level.txt
PLCSQL-0.7.dist-info/RECORD
