Metadata-Version: 2.1
Name: PLCSQL
Version: 0.7
Summary: This is package where you can build databases importing (mysql and mariadb) in python as easy
Author: PLC PEIRIS
Author-email: lashen985832@gmail.com
Classifier: Programming Language :: Python :: 3
Classifier: License :: OSI Approved :: MIT License
Classifier: Operating System :: OS Independent
License-File: license.txt
